README.md
setup.py
weibo.py
cave_weibo.egg-info/PKG-INFO
cave_weibo.egg-info/SOURCES.txt
cave_weibo.egg-info/dependency_links.txt
cave_weibo.egg-info/requires.txt
cave_weibo.egg-info/top_level.txt