Metadata-Version: 1.0
Name: cave-weibo
Version: 0.2.2
Summary: weibo base class. 微博 爬虫 基础
Home-page: https://github.com/lastcaveman/weibo
Author: lastcaveman
Author-email: caveman.last@gmail.com
License: MIT Licence
Keywords: pip,weibo,微博,爬虫
Platform: any
